pigeonview/__init__.py
pigeonview/data.py
pigeonview/persistence.py
tests/__init__.py
pigeonview-0.5.2.dist-info/LICENSE
pigeonview-0.5.2.dist-info/METADATA
pigeonview-0.5.2.dist-info/WHEEL
pigeonview-0.5.2.dist-info/top_level.txt
pigeonview-0.5.2.dist-info/RECORD
