Metadata-Version: 2.1
Name: pigeonview
Version: 0.5.2
Summary: Data monitoring
Home-page: https://github.com/bhky/pigeonview
Author: attr: pigeonview.__author__
Author-email: xtorch501@gmail.com
License: UNKNOWN
Platform: UNKNOWN
Classifier: Programming Language :: Python :: 3
Classifier: License :: OSI Approved :: MIT License
Classifier: Operating System :: OS Independent
Requires-Python: >=3.8
License-File: LICENSE
Requires-Dist: ipympl (>=0.9.0)
Requires-Dist: jupyterlab (>=3.0.0)
Requires-Dist: pandas (>=1.4.0)
Requires-Dist: psycopg2-binary (>=2.9.0)
